{
    "K": 25,
    "N": 625,
    "bp_converge_count_x": 1000,
    "bp_converge_count_z": 765,
    "bp_logical_error_rate": 0.241,
    "bp_logical_error_rate_eb": 0.013524755080961725,
    "bp_method": "ms",
    "bp_success_count": 759,
    "channel_update": null,
    "check_code": 1,
    "error_bar_precision_cutoff": 0.001,
    "error_rate": 0.05,
    "hadamard_rotate": 0,
    "hadamard_rotate_sector1_length": 0,
    "max_iter": 0,
    "min_logical_weight": 8,
    "ms_scaling_factor": 0,
    "osd0_logical_error_rate": 0.16800000000000004,
    "osd0_logical_error_rate_eb": 0.011822690049223148,
    "osd0_success_count": 832,
    "osd_method": "osd_cs",
    "osd_order": 42,
    "osdw_logical_error_rate": 0.04500000000000004,
    "osdw_logical_error_rate_eb": 0.00655553201502365,
    "osdw_success_count": 955,
    "osdw_word_error_rate": 0.0018400625453874886,
    "osdw_word_error_rate_eb": 0.00026388219146003923,
    "output_file": "montecarloresults//bposd//mkmn_20_5_8error5.json",
    "run_count": 1000,
    "run_sim": 1,
    "runtime": 6.829437971115112,
    "runtime_readable": "00:00:06",
    "save_interval": 2,
    "seed": 42,
    "start_date": "Monday, April 08, 2024 13:34:22",
    "target_runs": 1000,
    "tqdm_disable": 0,
    "xyz_error_bias": [
        0,
        0,
        1
    ]
}
