{
    "K": 16,
    "N": 400,
    "bp_converge_count_x": 9256,
    "bp_converge_count_z": 9265,
    "bp_logical_error_rate": 0.17500000000000004,
    "bp_logical_error_rate_eb": 0.0037996710383926663,
    "bp_method": "ms",
    "bp_success_count": 8250,
    "channel_update": null,
    "check_code": 1,
    "error_bar_precision_cutoff": 0.001,
    "error_rate": 0.05,
    "hadamard_rotate": 0,
    "hadamard_rotate_sector1_length": 0,
    "max_iter": 0,
    "min_logical_weight": 6,
    "ms_scaling_factor": 0,
    "osd0_logical_error_rate": 0.12060000000000004,
    "osd0_logical_error_rate_eb": 0.0032566184916259385,
    "osd0_success_count": 8794,
    "osd_method": "osd_cs",
    "osd_order": 42,
    "osdw_logical_error_rate": 0.06120000000000003,
    "osdw_logical_error_rate_eb": 0.002396968084893915,
    "osdw_success_count": 9388,
    "osdw_word_error_rate": 0.003939271570827962,
    "osdw_word_error_rate_eb": 0.00015014793667479705,
    "output_file": "mkmn_16_4_6error5.json",
    "run_count": 10000,
    "run_sim": 1,
    "runtime": 21.16965126991272,
    "runtime_readable": "00:00:21",
    "save_interval": 2,
    "seed": 42,
    "start_date": "Monday, March 25, 2024 19:38:36",
    "target_runs": 10000,
    "tqdm_disable": 0,
    "xyz_error_bias": [
        1,
        1,
        1
    ]
}
